curcheck/__init__.py
curcheck/config.py
curcheck/dispatcher.py
curcheck/errors.py
curcheck/events.py
curcheck/gui.py
curcheck/middlewares.py
curcheck/router.py
curcheck/utils.py
curcheck-1.2.0.dist-info/LICENSE.md
curcheck-1.2.0.dist-info/METADATA
curcheck-1.2.0.dist-info/WHEEL
curcheck-1.2.0.dist-info/RECORD
