Metadata-Version: 2.1
Name: curcheck
Version: 1.2.0
Summary: Library for parsing SPA and MPA sites
License: MIT
Author: BulatXam
Author-email: Khamdbulat@yandex.ru
Requires-Python: >=3.7
Classifier: License :: OSI Approved :: MIT License
Classifier: Programming Language :: Python :: 3
Classifier: Programming Language :: Python :: 3.7
Classifier: Programming Language :: Python :: 3.8
Classifier: Programming Language :: Python :: 3.9
Classifier: Programming Language :: Python :: 3.10
Classifier: Programming Language :: Python :: 3.11
Requires-Dist: aiohttp (>=3.8.3)
Requires-Dist: lxml (>=4.9.2)
Requires-Dist: pyppeteer (>=1.0.2)
